conda_manager-0.4.0-py3.5-nspkg.pth
conda_manager/__init__.py
conda_manager/_version.py
conda_manager/api/__init__.py
conda_manager/api/client_api.py
conda_manager/api/conda_api.py
conda_manager/api/download_api.py
conda_manager/api/manager_api.py
conda_manager/app/__init__.py
conda_manager/app/main.py
conda_manager/data/__init__.py
conda_manager/data/images/__init__.py
conda_manager/data/images/anaconda.png
conda_manager/data/images/conda_action_add.png
conda_manager/data/images/conda_action_downgrade.png
conda_manager/data/images/conda_action_installed.png
conda_manager/data/images/conda_action_installed_upgradable.png
conda_manager/data/images/conda_action_not_installed.png
conda_manager/data/images/conda_action_remove.png
conda_manager/data/images/conda_action_upgrade.png
conda_manager/data/images/conda_add_active.png
conda_manager/data/images/conda_add_inactive.png
conda_manager/data/images/conda_add_pressed.png
conda_manager/data/images/conda_bitbucket.png
conda_manager/data/images/conda_del.png
conda_manager/data/images/conda_docs.png
conda_manager/data/images/conda_downgrade_active.png
conda_manager/data/images/conda_downgrade_inactive.png
conda_manager/data/images/conda_downgrade_pressed.png
conda_manager/data/images/conda_github.png
conda_manager/data/images/conda_remove_active.png
conda_manager/data/images/conda_remove_inactive.png
conda_manager/data/images/conda_remove_pressed.png
conda_manager/data/images/conda_search.png
conda_manager/data/images/conda_upgrade_active.png
conda_manager/data/images/conda_upgrade_arrow.png
conda_manager/data/images/conda_upgrade_inactive.png
conda_manager/data/images/conda_upgrade_pressed.png
conda_manager/data/images/condapackages.png
conda_manager/data/images/home.png
conda_manager/data/images/python.png
conda_manager/data/repodata/__init__.py
conda_manager/data/repodata/_free_linux-32.json
conda_manager/data/repodata/_free_linux-64.json
conda_manager-0.4.0.dist-info/DESCRIPTION.rst
conda_manager-0.4.0.dist-info/METADATA
conda_manager-0.4.0.dist-info/RECORD
conda_manager-0.4.0.dist-info/WHEEL
conda_manager-0.4.0.dist-info/entry_points.txt
conda_manager-0.4.0.dist-info/metadata.json
conda_manager-0.4.0.dist-info/namespace_packages.txt
conda_manager-0.4.0.dist-info/top_level.txt
