Metadata-Version: 1.1
Name: conda-manager
Version: 0.4.0
Summary: A stand alone PyQt/PySide GUI application for managing conda packages and environments.
Home-page: https://github.com/spyder-ide/conda-manager
Author: Gonzalo Peña-Castellanos
Author-email: goanpeca@gmail.com
License: MIT
Keywords: Qt PyQt4 PyQt5 PySide conda conda-api binstar
Platform: UNKNOWN
Classifier: Development Status :: 4 - Beta
Classifier: Environment :: X11 Applications :: Qt
Classifier: Environment :: Win32 (MS Windows)
Classifier: Intended Audience :: Developers
Classifier: License :: OSI Approved :: MIT License
Classifier: Operating System :: OS Independent
Classifier: Programming Language :: Python :: 2
Classifier: Programming Language :: Python :: 2.7
Classifier: Programming Language :: Python :: 3
Classifier: Programming Language :: Python :: 3.4
Classifier: Programming Language :: Python :: 3.5
Classifier: Topic :: Software Development :: Widget Sets
